incantations/__init__.py
incantations/collections.py
incantations-0.0.1.dist-info/METADATA
incantations-0.0.1.dist-info/WHEEL
incantations-0.0.1.dist-info/licenses/LICENSE
incantations-0.0.1.dist-info/RECORD
