Metadata-Version: 2.3
Name: incantations
Version: 0.0.1
Summary: A mystical collection of powerful utility functions for everyday coding wizardry
Project-URL: Homepage, https://github.com/mliezun/incantations
Project-URL: Bug Tracker, https://github.com/mliezun/incantations/issues
Author-email: Miguel Liezun <liezun.js@gmail.com>
License-File: LICENSE
Classifier: License :: OSI Approved :: MIT License
Classifier: Operating System :: OS Independent
Classifier: Programming Language :: Python :: 3
Requires-Python: >=3.7
